nrel_phygnn-0.0.33.dist-info/licenses/LICENSE
phygnn/__init__.py
phygnn/_version.py
phygnn/base.py
phygnn/phygnn.py
phygnn/version.py
phygnn/layers/__init__.py
phygnn/layers/custom_layers.py
phygnn/layers/handlers.py
phygnn/model_interfaces/__init__.py
phygnn/model_interfaces/base_model.py
phygnn/model_interfaces/phygnn_model.py
phygnn/model_interfaces/random_forest_model.py
phygnn/model_interfaces/tf_model.py
phygnn/utilities/__init__.py
phygnn/utilities/loss_metrics.py
phygnn/utilities/pre_processing.py
phygnn/utilities/tf_utilities.py
nrel_phygnn-0.0.33.dist-info/METADATA
nrel_phygnn-0.0.33.dist-info/WHEEL
nrel_phygnn-0.0.33.dist-info/top_level.txt
nrel_phygnn-0.0.33.dist-info/RECORD
