Metadata-Version: 2.4
Name: NREL-phygnn
Version: 0.0.33
Summary: Physics-Guided Neural Networks (phygnn)
Author-email: Grant Buster <grant.buster@nrel.gov>
License: BSD-3-Clause
Project-URL: homepage, https://github.com/NREL/phygnn
Project-URL: documentation, https://nrel.github.io/phygnn/
Project-URL: repository, https://github.com/NREL/phygnn
Keywords: phygnn,NREL
Classifier: Development Status :: 4 - Beta
Classifier: Intended Audience :: Science/Research
Classifier: License :: OSI Approved :: BSD License
Classifier: Natural Language :: English
Classifier: Programming Language :: Python :: 3.8
Classifier: Programming Language :: Python :: 3.9
Classifier: Programming Language :: Python :: 3.10
Classifier: Programming Language :: Python :: 3.11
Requires-Python: >=3.8
License-File: LICENSE
Requires-Dist: matplotlib>=3.1
Requires-Dist: NREL-rex
Requires-Dist: numpy>=1.16
Requires-Dist: pandas>=0.25
Requires-Dist: pytest>=5.2
Requires-Dist: scikit-learn>=1.2
Requires-Dist: tensorflow<2.16,>2.4
Provides-Extra: dev
Requires-Dist: build>=0.5; extra == "dev"
Requires-Dist: flake8; extra == "dev"
Requires-Dist: pre-commit; extra == "dev"
Requires-Dist: pylint; extra == "dev"
Provides-Extra: doc
Requires-Dist: sphinx>=7.0; extra == "doc"
Requires-Dist: sphinx-click>=4.0; extra == "doc"
Requires-Dist: sphinx-book-theme>=1.1.1; extra == "doc"
Requires-Dist: sphinx_autosummary_accessors>=2023.4.0; extra == "doc"
Provides-Extra: test
Requires-Dist: pytest>=5.2; extra == "test"
Requires-Dist: pytest-env; extra == "test"
Dynamic: license-file
